{"name":"aromatisse","id":683,"order":795,"height":8,"stats":{"hp":101,"attack":72,"defense":72,"special-attack":99,"special-defense":89,"speed":29},"types":{"type1":"fairy","type2":"null"},"abilities":{"base":["healer"],"hidden":["aroma-veil"]},"moves":[{"name":"hyper-beam","level":0},{"name":"thunderbolt","level":0},{"name":"thunder","level":0},{"name":"toxic","level":0},{"name":"psychic","level":48},{"name":"double-team","level":0},{"name":"light-screen","level":0},{"name":"reflect","level":57},{"name":"dream-eater","level":0},{"name":"flash","level":0},{"name":"rest","level":0},{"name":"substitute","level":0},{"name":"snore","level":0},{"name":"flail","level":38},{"name":"protect","level":0},{"name":"sweet-kiss","level":6},{"name":"charm","level":35},{"name":"swagger","level":0},{"name":"attract","level":29},{"name":"sleep-talk","level":0},{"name":"heal-bell","level":0},{"name":"return","level":0},{"name":"frustration","level":0},{"name":"sweet-scent","level":1},{"name":"hidden-power","level":0},{"name":"rain-dance","level":0},{"name":"sunny-day","level":0},{"name":"psych-up","level":64},{"name":"torment","level":0},{"name":"facade","level":0},{"name":"helping-hand","level":0},{"name":"magic-coat","level":0},{"name":"endeavor","level":0},{"name":"skill-swap","level":44},{"name":"secret-power","level":0},{"name":"aromatherapy","level":25},{"name":"odor-sleuth","level":8},{"name":"covet","level":0},{"name":"calm-mind","level":17},{"name":"gyro-ball","level":0},{"name":"drain-punch","level":0},{"name":"energy-ball","level":0},{"name":"giga-impact","level":0},{"name":"flash-cannon","level":0},{"name":"trick-room","level":0},{"name":"charge-beam","level":0},{"name":"psyshock","level":0},{"name":"after-you","level":0},{"name":"round","level":0},{"name":"echoed-voice","level":13},{"name":"heal-pulse","level":1},{"name":"disarming-voice","level":53},{"name":"draining-kiss","level":21},{"name":"misty-terrain","level":42},{"name":"fairy-wind","level":1},{"name":"moonblast","level":31},{"name":"confide","level":0},{"name":"aromatic-mist","level":1},{"name":"dazzling-gleam","level":0}],"sprites":{"default_sprite":"https://raw.githubusercontent.com/PokeAPI/sprites/master/sprites/pokemon/683.png","shiny_sprite":"https://raw.githubusercontent.com/PokeAPI/sprites/master/sprites/pokemon/shiny/683.png","art":"https://raw.githubusercontent.com/PokeAPI/sprites/master/sprites/pokemon/other/official-artwork/683.png"}}