{"name":"seaking","id":119,"order":180,"height":13,"stats":{"hp":80,"attack":92,"defense":65,"special-attack":65,"special-defense":80,"speed":68},"types":{"type1":"water","type2":"null"},"abilities":{"base":["swift-swim","water-veil"],"hidden":["lightning-rod"]},"moves":[{"name":"horn-attack","level":24},{"name":"fury-attack","level":30},{"name":"horn-drill","level":48},{"name":"take-down","level":0},{"name":"double-edge","level":0},{"name":"tail-whip","level":1},{"name":"supersonic","level":1},{"name":"water-gun","level":0},{"name":"surf","level":0},{"name":"ice-beam","level":0},{"name":"blizzard","level":0},{"name":"bubble-beam","level":0},{"name":"hyper-beam","level":0},{"name":"peck","level":1},{"name":"toxic","level":0},{"name":"agility","level":54},{"name":"rage","level":0},{"name":"mimic","level":0},{"name":"double-team","level":0},{"name":"bide","level":0},{"name":"waterfall","level":39},{"name":"swift","level":0},{"name":"skull-bash","level":0},{"name":"rest","level":0},{"name":"substitute","level":0},{"name":"snore","level":0},{"name":"curse","level":0},{"name":"flail","level":24},{"name":"protect","level":0},{"name":"mud-slap","level":0},{"name":"icy-wind","level":0},{"name":"endure","level":0},{"name":"swagger","level":0},{"name":"fury-cutter","level":0},{"name":"attract","level":0},{"name":"sleep-talk","level":0},{"name":"return","level":0},{"name":"frustration","level":0},{"name":"megahorn","level":69},{"name":"hidden-power","level":0},{"name":"rain-dance","level":0},{"name":"whirlpool","level":0},{"name":"hail","level":0},{"name":"facade","level":0},{"name":"knock-off","level":0},{"name":"secret-power","level":0},{"name":"dive","level":0},{"name":"signal-beam","level":0},{"name":"bounce","level":0},{"name":"water-sport","level":1},{"name":"water-pulse","level":0},{"name":"natural-gift","level":0},{"name":"aqua-ring","level":27},{"name":"poison-jab","level":1},{"name":"aqua-tail","level":0},{"name":"giga-impact","level":0},{"name":"captivate","level":0},{"name":"soak","level":63},{"name":"round","level":0},{"name":"scald","level":0},{"name":"drill-run","level":0},{"name":"confide","level":0},{"name":"smart-strike","level":0}],"sprites":{"default_sprite":"https://raw.githubusercontent.com/PokeAPI/sprites/master/sprites/pokemon/119.png","shiny_sprite":"https://raw.githubusercontent.com/PokeAPI/sprites/master/sprites/pokemon/shiny/119.png","art":"https://raw.githubusercontent.com/PokeAPI/sprites/master/sprites/pokemon/other/official-artwork/119.png"}}