{"name":"weepinbell","id":70,"order":108,"height":10,"stats":{"hp":65,"attack":90,"defense":50,"special-attack":85,"special-defense":45,"speed":55},"types":{"type1":"grass","type2":"poison"},"abilities":{"base":["chlorophyll"],"hidden":["gluttony"]},"moves":[{"name":"swords-dance","level":0},{"name":"cut","level":0},{"name":"bind","level":0},{"name":"slam","level":49},{"name":"vine-whip","level":1},{"name":"wrap","level":1},{"name":"take-down","level":0},{"name":"double-edge","level":0},{"name":"acid","level":29},{"name":"mega-drain","level":0},{"name":"growth","level":1},{"name":"razor-leaf","level":38},{"name":"solar-beam","level":0},{"name":"poison-powder","level":15},{"name":"stun-spore","level":23},{"name":"sleep-powder","level":18},{"name":"toxic","level":0},{"name":"rage","level":0},{"name":"mimic","level":0},{"name":"double-team","level":0},{"name":"reflect","level":0},{"name":"bide","level":0},{"name":"flash","level":0},{"name":"rest","level":0},{"name":"substitute","level":0},{"name":"thief","level":0},{"name":"snore","level":0},{"name":"curse","level":0},{"name":"protect","level":0},{"name":"sludge-bomb","level":0},{"name":"giga-drain","level":0},{"name":"endure","level":0},{"name":"swagger","level":0},{"name":"attract","level":0},{"name":"sleep-talk","level":0},{"name":"return","level":0},{"name":"frustration","level":0},{"name":"sweet-scent","level":33},{"name":"synthesis","level":0},{"name":"hidden-power","level":0},{"name":"sunny-day","level":0},{"name":"facade","level":0},{"name":"nature-power","level":0},{"name":"knock-off","level":27},{"name":"secret-power","level":0},{"name":"bullet-seed","level":0},{"name":"natural-gift","level":0},{"name":"wring-out","level":47},{"name":"gastro-acid","level":35},{"name":"worry-seed","level":0},{"name":"sucker-punch","level":0},{"name":"poison-jab","level":47},{"name":"seed-bomb","level":0},{"name":"energy-ball","level":0},{"name":"captivate","level":0},{"name":"grass-knot","level":0},{"name":"bug-bite","level":0},{"name":"venoshock","level":0},{"name":"round","level":0},{"name":"confide","level":0},{"name":"infestation","level":0}],"sprites":{"default_sprite":"https://raw.githubusercontent.com/PokeAPI/sprites/master/sprites/pokemon/70.png","shiny_sprite":"https://raw.githubusercontent.com/PokeAPI/sprites/master/sprites/pokemon/shiny/70.png","art":"https://raw.githubusercontent.com/PokeAPI/sprites/master/sprites/pokemon/other/official-artwork/70.png"}}